ch/__init__.pyi
ch/py.typed
ch/qos/__init__.pyi
ch/qos/logback/__init__.pyi
ch/qos/logback/classic/__init__.pyi
com/__init__.pyi
com/py.typed
com/codahale/__init__.pyi
com/codahale/metrics/__init__.pyi
com/google/__init__.pyi
com/google/common/__init__.pyi
com/google/common/collect/__init__.pyi
com/google/common/eventbus/__init__.pyi
com/google/common/util/__init__.pyi
com/google/common/util/concurrent/__init__.pyi
com/inductiveautomation/__init__.pyi
com/inductiveautomation/factorypmi/__init__.pyi
com/inductiveautomation/factorypmi/application/__init__.pyi
com/inductiveautomation/factorypmi/application/binding/__init__.pyi
com/inductiveautomation/factorypmi/application/components/__init__.pyi
com/inductiveautomation/factorypmi/application/model/__init__.pyi
com/inductiveautomation/factorypmi/application/script/__init__.pyi
com/inductiveautomation/factorypmi/application/script/builtin/__init__.pyi
com/inductiveautomation/factorypmi/application/sqltags/__init__.pyi
com/inductiveautomation/factorypmi/application/sqltags/project/__init__.pyi
com/inductiveautomation/ignition/__init__.pyi
com/inductiveautomation/ignition/alarming/__init__.pyi
com/inductiveautomation/ignition/alarming/common/__init__.pyi
com/inductiveautomation/ignition/alarming/common/rosters/__init__.pyi
com/inductiveautomation/ignition/client/__init__.pyi
com/inductiveautomation/ignition/client/launch/__init__.pyi
com/inductiveautomation/ignition/client/model/__init__.pyi
com/inductiveautomation/ignition/client/util/__init__.pyi
com/inductiveautomation/ignition/client/util/gui/__init__.pyi
com/inductiveautomation/ignition/client/util/gui/progress/__init__.pyi
com/inductiveautomation/ignition/client/util/gui/scheduling/__init__.pyi
com/inductiveautomation/ignition/common/__init__.pyi
com/inductiveautomation/ignition/common/alarming/__init__.pyi
com/inductiveautomation/ignition/common/alarming/evaluation/__init__.pyi
com/inductiveautomation/ignition/common/alarming/query/__init__.pyi
ignition_api_stubs-8.3.3.dist-info/licenses/LICENSE
ignition_api_stubs-8.3.3.dist-info/METADATA
ignition_api_stubs-8.3.3.dist-info/WHEEL
ignition_api_stubs-8.3.3.dist-info/top_level.txt
ignition_api_stubs-8.3.3.dist-info/RECORD
