Metadata-Version: 2.4
Name: ignition-api-stubs
Version: 8.3.3
Summary: Ignition Scripting API Stubs
Author-email: César Román <cesar@coatl.dev>
License-Expression: MIT
Project-URL: Documentation, https://docs.inductiveautomation.com/docs/8.3/appendix/scripting-functions
Project-URL: Funding, https://github.com/sponsors/cesarcoatl
Project-URL: Source, https://github.com/ignition-devs/ignition-api/tree/8.3
Project-URL: Tracker, https://github.com/ignition-devs/ignition-api/issues
Keywords: hmi,ignition,inductive automation,scada
Classifier: Development Status :: 5 - Production/Stable
Classifier: Intended Audience :: Developers
Classifier: Intended Audience :: Information Technology
Classifier: Intended Audience :: Manufacturing
Classifier: Operating System :: MacOS :: MacOS X
Classifier: Operating System :: Microsoft :: Windows
Classifier: Operating System :: POSIX :: Linux
Classifier: Programming Language :: Python
Classifier: Programming Language :: Python :: 3 :: Only
Classifier: Programming Language :: Python :: 3.9
Classifier: Programming Language :: Python :: 3.10
Classifier: Programming Language :: Python :: 3.11
Classifier: Programming Language :: Python :: 3.12
Classifier: Typing :: Stubs Only
Classifier: Typing :: Typed
Requires-Python: <3.13,>=3.9
License-File: LICENSE
Requires-Dist: java-api-stubs
Requires-Dist: types-enum34
Dynamic: license-file
